README.md
setup.py
visionui/__about__.py
visionui/__init__.py
visionui.egg-info/PKG-INFO
visionui.egg-info/SOURCES.txt
visionui.egg-info/dependency_links.txt
visionui.egg-info/requires.txt
visionui.egg-info/top_level.txt
visionui/api/__init__.py
visionui/api/vision_api.py
visionui/dbnet_crnn/__init__.py
visionui/dbnet_crnn/image_text.py
visionui/dbnet_crnn/model/det/model
visionui/dbnet_crnn/model/det/params
visionui/dbnet_crnn/model/rec/model
visionui/dbnet_crnn/model/rec/params
visionui/dbnet_crnn/ppocr/__init__.py
visionui/dbnet_crnn/ppocr/db_post_process.py
visionui/dbnet_crnn/ppocr/db_process.py
visionui/dbnet_crnn/ppocr/utils/__init__.py
visionui/dbnet_crnn/ppocr/utils/character.py
visionui/dbnet_crnn/ppocr/utils/keys.txt
visionui/dbnet_crnn/tools/__init__.py
visionui/dbnet_crnn/tools/predict_det.py
visionui/dbnet_crnn/tools/predict_rec.py
visionui/dbnet_crnn/tools/utility.py
visionui/service/__init__.py
visionui/service/image_diff.py
visionui/service/image_merge.py
visionui/service/image_similar.py
visionui/service/image_text.py
visionui/service/image_utils.py