Metadata-Version: 2.1
Name: visionui
Version: 2.1.6
Summary: A line-oriented image diff algorithm.
Home-page: https://github.com/Meituan-Dianping/vision-ui
Author: tech@meituan.com
Author-email:  tech@meituan.com
License: MIT
Keywords: A line-oriented image diff algorithm
Platform: UNKNOWN
Classifier: Development Status :: 3 - Alpha
Classifier: Programming Language :: Python :: 2.7
Classifier: Programming Language :: Python :: 3.4
Classifier: Programming Language :: Python :: 3.5
Classifier: Programming Language :: Python :: 3.6
Classifier: Programming Language :: Python :: 3.7
Requires-Python: >=2.7, !=3.0.*, !=3.1.*, !=3.2.*, !=3.3.*, <4
